dnnpy/__init__.py
dnnpy/activations.py
dnnpy/data.py
dnnpy/fun_utils.py
dnnpy/im2col.py
dnnpy/layers.py
dnnpy/loss_functions.py
dnnpy/metrics.py
dnnpy/optimizers.py
dnnpy/train.py
dnnpy/utils.py
dnnpy-0.0.1.dist-info/LICENCE
dnnpy-0.0.1.dist-info/METADATA
dnnpy-0.0.1.dist-info/WHEEL
dnnpy-0.0.1.dist-info/top_level.txt
dnnpy-0.0.1.dist-info/RECORD
