Metadata-Version: 2.1
Name: dnnpy
Version: 0.0.1
Summary: Pytorch-like Neural Network framework
Home-page: UNKNOWN
Author: Urchade Zaratiana
Author-email: urchade.zaratiana@gmail.com
License: UNKNOWN
Platform: UNKNOWN
Classifier: Programming Language :: Python :: 3
Classifier: License :: OSI Approved :: MIT License
Classifier: Operating System :: OS Independent
Requires-Python: >=3.6
